{
  "version": "7",
  "dialect": "postgresql",
  "entries": [
    {
      "idx": 0,
      "version": "7",
      "when": 1772636372693,
      "tag": "0000_giant_mathemanic",
      "breakpoints": true
    },
    {
      "idx": 1,
      "version": "7",
      "when": 1772903420544,
      "tag": "0001_marvelous_cammi",
      "breakpoints": true
    },
    {
      "idx": 2,
      "version": "7",
      "when": 1741689600000,
      "tag": "0002_add_analysis_jobs",
      "breakpoints": true
    },
    {
      "idx": 3,
      "version": "7",
      "when": 1742256000000,
      "tag": "0003_add_policies_categories",
      "breakpoints": true
    },
    {
      "idx": 4,
      "version": "7",
      "when": 1742515200000,
      "tag": "0004_drop_assurance",
      "breakpoints": true
    },
    {
      "idx": 5,
      "version": "7",
      "when": 1742522400000,
      "tag": "0005_pivot_outcomes",
      "breakpoints": true
    }
  ]
}